LICENSE
README.md
setup.cfg
setup.py
pyjmap/__init__.py
pyjmap/__main__.py
pyjmap/jmap.py
pyjmap/lookup_donkeykongjunglebeat.txt
pyjmap/lookup_luigismansion.txt
pyjmap/lookup_supermariogalaxy.txt
pyjmap/lookup_supermariosunshine.txt
pyjmap.egg-info/PKG-INFO
pyjmap.egg-info/SOURCES.txt
pyjmap.egg-info/dependency_links.txt
pyjmap.egg-info/entry_points.txt
pyjmap.egg-info/top_level.txt