Metadata-Version: 2.1
Name: pyjmap
Version: 1.0.9
Summary: Python library for Nintendo's BCSV/JMap format
Home-page: https://github.com/SunakazeKun/pyjmap
Author: Aurum
License: gpl-3.0
Keywords: nintendo,jsystem,jmap,bcsv,modding
Classifier: Intended Audience :: Developers
Classifier: Topic :: Software Development :: Libraries
Classifier: License :: OSI Approved :: GNU General Public License v3 (GPLv3)
Classifier: Programming Language :: Python :: 3 :: Only
Requires-Python: >=3.6
License-File: LICENSE
